Assignment 1 2025EET2478/Verilogfiles(GROUP_C)/hash.v
                                         //HASHING MODULE//

//what is hashing here?
/* Hashing is one of the functions (typically mathematical) that helps to keep the sensitive information and
the data. It fixes a output using a hash function based on the input data. */


module hash_spn(
    input wire [7:0] data_in,                //takes the 8-bit Encrypted byte from the encrypt module
    output wire [7:0] hash_out,                 //final 8-bit Hash output
    output wire [7:0] xor_val,                  //intermediate debugging signal (result after xoring with the key)
    output wire [7:0] shifted_val               //intermediate debugging signal (result after the left shift)
);

parameter KEY=8'h5A;


//--------------------------XORing with the key----------------------------------------

function [7:0] xoring_withthe_key;
input [7:0]val;
xoring_withthe_key= val^KEY;
endfunction


//--------------------------Shifting left with 2 (moduluo 256)----------------------------

function [7:0] left_shiftingby_2;
input [7:0] val;
left_shiftingby_2=(val<<2) & 8'hFF;     //(using 8'hFF for avoiding the overflow....it is just like modulo 256)
endfunction

 
 //---------------------------Hashing pipeline-----------------------------------------------

 assign xor_val=xoring_withthe_key(data_in);
 assign shifted_val=left_shiftingby_2(xor_val);
 assign hash_out=shifted_val;

 endmodule

Assignment 1 2025EET2478/Verilogfiles(GROUP_C)/encrypt.v
                                            //ENCRYPTION MODULE//

//what is encryption here?
/*It is a way to protect the data or the important information with the help of 
some mathematical tools or models so that no third party users can access it wihtout the help of the key */

module encrypt_spn(
    input wire [7:0] data_input,           //the 8-bit input Plaintext
    output wire [7:0] data_output,         //the final 8- bit Ciphertext
    output wire [7:0] s_box_val,           //intermediate value after substituting from the s_box
    output wire [7:0] perm_val             //intermediate value after permuting 
);

  parameter KEY=8'h5A;                      //Fixed Round key

wire[7:0] xor_val;

//-------------HERE WE ARE SPLITTING THE NIBBLES INTO TWO 4-BIT VALUES-------------------------------

  function [3:0] get_upper;
  input [7:0] in;
  get_upper=in[7:4];
  endfunction;

  function [3:0] get_lower;
  input [7:0] in;
  get_lower=in[3:0];
  endfunction;

  function [7:0] mergingnibbles;
  input [3:0] high,low;
  mergingnibbles={high,low};
  endfunction;


//----------------AES S-BOX LOOKUP TABLE-----------------------------------

function [7:0] s_box_lookup;
input [7:0] in;
begin 
    case(in)
        8'h00: s_box_lookup = 8'h63; 8'h01: s_box_lookup = 8'h7C; 8'h02: s_box_lookup = 8'h77; 8'h03: s_box_lookup = 8'h7B;
        8'h04: s_box_lookup = 8'hF2; 8'h05: s_box_lookup = 8'h6B; 8'h06: s_box_lookup = 8'h6F; 8'h07: s_box_lookup = 8'hC5;
        8'h08: s_box_lookup = 8'h30; 8'h09: s_box_lookup = 8'h01; 8'h0A: s_box_lookup = 8'h67; 8'h0B: s_box_lookup = 8'h2B;
        8'h0C: s_box_lookup = 8'hFE; 8'h0D: s_box_lookup = 8'hD7; 8'h0E: s_box_lookup = 8'hAB; 8'h0F: s_box_lookup = 8'h76;

        8'h10: s_box_lookup = 8'hCA; 8'h11: s_box_lookup = 8'h82; 8'h12: s_box_lookup = 8'hC9; 8'h13: s_box_lookup = 8'h7D;
        8'h14: s_box_lookup = 8'hFA; 8'h15: s_box_lookup = 8'h59; 8'h16: s_box_lookup = 8'h47; 8'h17: s_box_lookup = 8'hF0;
        8'h18: s_box_lookup = 8'hAD; 8'h19: s_box_lookup = 8'hD4; 8'h1A: s_box_lookup = 8'hA2; 8'h1B: s_box_lookup = 8'hAF;
        8'h1C: s_box_lookup = 8'h9C; 8'h1D: s_box_lookup = 8'hA4; 8'h1E: s_box_lookup = 8'h72; 8'h1F: s_box_lookup = 8'hC0;

        8'h20: s_box_lookup = 8'hB7; 8'h21: s_box_lookup = 8'hFD; 8'h22: s_box_lookup = 8'h93; 8'h23: s_box_lookup = 8'h26;
        8'h24: s_box_lookup = 8'h36; 8'h25: s_box_lookup = 8'h3F; 8'h26: s_box_lookup = 8'hF7; 8'h27: s_box_lookup = 8'hCC;
        8'h28: s_box_lookup = 8'h34; 8'h29: s_box_lookup = 8'hA5; 8'h2A: s_box_lookup = 8'hE5; 8'h2B: s_box_lookup = 8'hF1;
        8'h2C: s_box_lookup = 8'h71; 8'h2D: s_box_lookup = 8'hD8; 8'h2E: s_box_lookup = 8'h31; 8'h2F: s_box_lookup = 8'h15;

        8'h30: s_box_lookup = 8'h04; 8'h31: s_box_lookup = 8'hC7; 8'h32: s_box_lookup = 8'h23; 8'h33: s_box_lookup = 8'hC3;
        8'h34: s_box_lookup = 8'h18; 8'h35: s_box_lookup = 8'h96; 8'h36: s_box_lookup = 8'h05; 8'h37: s_box_lookup = 8'h9A;
        8'h38: s_box_lookup = 8'h07; 8'h39: s_box_lookup = 8'h12; 8'h3A: s_box_lookup = 8'h80; 8'h3B: s_box_lookup = 8'hE2;
        8'h3C: s_box_lookup = 8'hEB; 8'h3D: s_box_lookup = 8'h27; 8'h3E: s_box_lookup = 8'hB2; 8'h3F: s_box_lookup = 8'h75;

        8'h40: s_box_lookup = 8'h09; 8'h41: s_box_lookup = 8'h83; 8'h42: s_box_lookup = 8'h2C; 8'h43: s_box_lookup = 8'h1A;
        8'h44: s_box_lookup = 8'h1B; 8'h45: s_box_lookup = 8'h6E; 8'h46: s_box_lookup = 8'h5A; 8'h47: s_box_lookup = 8'hA0;
        8'h48: s_box_lookup = 8'h52; 8'h49: s_box_lookup = 8'h3B; 8'h4A: s_box_lookup = 8'hD6; 8'h4B: s_box_lookup = 8'hB3;
        8'h4C: s_box_lookup = 8'h29; 8'h4D: s_box_lookup = 8'hE3; 8'h4E: s_box_lookup = 8'h2F; 8'h4F: s_box_lookup = 8'h84;

        8'h50: s_box_lookup = 8'h53; 8'h51: s_box_lookup = 8'hD1; 8'h52: s_box_lookup = 8'h00; 8'h53: s_box_lookup = 8'hED;
        8'h54: s_box_lookup = 8'h20; 8'h55: s_box_lookup = 8'hFC; 8'h56: s_box_lookup = 8'hB1; 8'h57: s_box_lookup = 8'h5B;
        8'h58: s_box_lookup = 8'h6A; 8'h59: s_box_lookup = 8'hCB; 8'h5A: s_box_lookup = 8'hBE; 8'h5B: s_box_lookup = 8'h39;
        8'h5C: s_box_lookup = 8'h4A; 8'h5D: s_box_lookup = 8'h4C; 8'h5E: s_box_lookup = 8'h58; 8'h5F: s_box_lookup = 8'hCF;

        8'h60: s_box_lookup = 8'hD0; 8'h61: s_box_lookup = 8'hEF; 8'h62: s_box_lookup = 8'hAA; 8'h63: s_box_lookup = 8'hFB;
        8'h64: s_box_lookup = 8'h43; 8'h65: s_box_lookup = 8'h4D; 8'h66: s_box_lookup = 8'h33; 8'h67: s_box_lookup = 8'h85;
        8'h68: s_box_lookup = 8'h45; 8'h69: s_box_lookup = 8'hF9; 8'h6A: s_box_lookup = 8'h02; 8'h6B: s_box_lookup = 8'h7F;
        8'h6C: s_box_lookup = 8'h50; 8'h6D: s_box_lookup = 8'h3C; 8'h6E: s_box_lookup = 8'h9F; 8'h6F: s_box_lookup = 8'hA8;

        8'h70: s_box_lookup = 8'h51; 8'h71: s_box_lookup = 8'hA3; 8'h72: s_box_lookup = 8'h40; 8'h73: s_box_lookup = 8'h8F;
        8'h74: s_box_lookup = 8'h92; 8'h75: s_box_lookup = 8'h9D; 8'h76: s_box_lookup = 8'h38; 8'h77: s_box_lookup = 8'hF5;
        8'h78: s_box_lookup = 8'hBC; 8'h79: s_box_lookup = 8'hB6; 8'h7A: s_box_lookup = 8'hDA; 8'h7B: s_box_lookup = 8'h21;
        8'h7C: s_box_lookup = 8'h10; 8'h7D: s_box_lookup = 8'hFF; 8'h7E: s_box_lookup = 8'hF3; 8'h7F: s_box_lookup = 8'hD2;

        8'h80: s_box_lookup = 8'hCD; 8'h81: s_box_lookup = 8'h0C; 8'h82: s_box_lookup = 8'h13; 8'h83: s_box_lookup = 8'hEC;
        8'h84: s_box_lookup = 8'h5F; 8'h85: s_box_lookup = 8'h97; 8'h86: s_box_lookup = 8'h44; 8'h87: s_box_lookup = 8'h17;
        8'h88: s_box_lookup = 8'hC4; 8'h89: s_box_lookup = 8'hA7; 8'h8A: s_box_lookup = 8'h7E; 8'h8B: s_box_lookup = 8'h3D;
        8'h8C: s_box_lookup = 8'h64; 8'h8D: s_box_lookup = 8'h5D; 8'h8E: s_box_lookup = 8'h19; 8'h8F: s_box_lookup = 8'h73;

        8'h90: s_box_lookup = 8'h60; 8'h91: s_box_lookup = 8'h81; 8'h92: s_box_lookup = 8'h4F; 8'h93: s_box_lookup = 8'hDC;
        8'h94: s_box_lookup = 8'h22; 8'h95: s_box_lookup = 8'h2A; 8'h96: s_box_lookup = 8'h90; 8'h97: s_box_lookup = 8'h88;
        8'h98: s_box_lookup = 8'h46; 8'h99: s_box_lookup = 8'hEE; 8'h9A: s_box_lookup = 8'hB8; 8'h9B: s_box_lookup = 8'h14;
        8'h9C: s_box_lookup = 8'hDE; 8'h9D: s_box_lookup = 8'h5E; 8'h9E: s_box_lookup = 8'h0B; 8'h9F: s_box_lookup = 8'hDB;

        8'hA0: s_box_lookup = 8'hE0; 8'hA1: s_box_lookup = 8'h32; 8'hA2: s_box_lookup = 8'h3A; 8'hA3: s_box_lookup = 8'h0A;
        8'hA4: s_box_lookup = 8'h49; 8'hA5: s_box_lookup = 8'h06; 8'hA6: s_box_lookup = 8'h24; 8'hA7: s_box_lookup = 8'h5C;
        8'hA8: s_box_lookup = 8'hC2; 8'hA9: s_box_lookup = 8'hD3; 8'hAA: s_box_lookup = 8'hAC; 8'hAB: s_box_lookup = 8'h62;
        8'hAC: s_box_lookup = 8'h91; 8'hAD: s_box_lookup = 8'h95; 8'hAE: s_box_lookup = 8'hE4; 8'hAF: s_box_lookup = 8'h79;

        8'hB0: s_box_lookup = 8'hE7; 8'hB1: s_box_lookup = 8'hC8; 8'hB2: s_box_lookup = 8'h37; 8'hB3: s_box_lookup = 8'h6D;
        8'hB4: s_box_lookup = 8'h8D; 8'hB5: s_box_lookup = 8'hD5; 8'hB6: s_box_lookup = 8'h4E; 8'hB7: s_box_lookup = 8'hA9;
        8'hB8: s_box_lookup = 8'h6C; 8'hB9: s_box_lookup = 8'h56; 8'hBA: s_box_lookup = 8'hF4; 8'hBB: s_box_lookup = 8'hEA;
        8'hBC: s_box_lookup = 8'h65; 8'hBD: s_box_lookup = 8'h7A; 8'hBE: s_box_lookup = 8'hAE; 8'hBF: s_box_lookup = 8'h08;

        8'hC0: s_box_lookup = 8'hBA; 8'hC1: s_box_lookup = 8'h78; 8'hC2: s_box_lookup = 8'h25; 8'hC3: s_box_lookup = 8'h2E;
        8'hC4: s_box_lookup = 8'h1C; 8'hC5: s_box_lookup = 8'hA6; 8'hC6: s_box_lookup = 8'hB4; 8'hC7: s_box_lookup = 8'hC6;
        8'hC8: s_box_lookup = 8'hE8; 8'hC9: s_box_lookup = 8'hDD; 8'hCA: s_box_lookup = 8'h74; 8'hCB: s_box_lookup = 8'h1F;
        8'hCC: s_box_lookup = 8'h4B; 8'hCD: s_box_lookup = 8'hBD; 8'hCE: s_box_lookup = 8'h8B; 8'hCF: s_box_lookup = 8'h8A;

        8'hD0: s_box_lookup = 8'h70; 8'hD1: s_box_lookup = 8'h3E; 8'hD2: s_box_lookup = 8'hB5; 8'hD3: s_box_lookup = 8'h66;
        8'hD4: s_box_lookup = 8'h48; 8'hD5: s_box_lookup = 8'h03; 8'hD6: s_box_lookup = 8'hF6; 8'hD7: s_box_lookup = 8'h0E;
        8'hD8: s_box_lookup = 8'h61; 8'hD9: s_box_lookup = 8'h35; 8'hDA: s_box_lookup = 8'h57; 8'hDB: s_box_lookup = 8'hB9;
        8'hDC: s_box_lookup = 8'h86; 8'hDD: s_box_lookup = 8'hC1; 8'hDE: s_box_lookup = 8'h1D; 8'hDF: s_box_lookup = 8'h9E;

        8'hE0: s_box_lookup = 8'hE1; 8'hE1: s_box_lookup = 8'hF8; 8'hE2: s_box_lookup = 8'h98; 8'hE3: s_box_lookup = 8'h11;
        8'hE4: s_box_lookup = 8'h69; 8'hE5: s_box_lookup = 8'hD9; 8'hE6: s_box_lookup = 8'h8E; 8'hE7: s_box_lookup = 8'h94;
        8'hE8: s_box_lookup = 8'h9B; 8'hE9: s_box_lookup = 8'h1E; 8'hEA: s_box_lookup = 8'h87; 8'hEB: s_box_lookup = 8'hE9;
        8'hEC: s_box_lookup = 8'hCE; 8'hED: s_box_lookup = 8'h55; 8'hEE: s_box_lookup = 8'h28; 8'hEF: s_box_lookup = 8'hDF;

        8'hF0: s_box_lookup = 8'h8C; 8'hF1: s_box_lookup = 8'hA1; 8'hF2: s_box_lookup = 8'h89; 8'hF3: s_box_lookup = 8'h0D;
        8'hF4: s_box_lookup = 8'hBF; 8'hF5: s_box_lookup = 8'hE6; 8'hF6: s_box_lookup = 8'h42; 8'hF7: s_box_lookup = 8'h68;
        8'hF8: s_box_lookup = 8'h41; 8'hF9: s_box_lookup = 8'h99; 8'hFA: s_box_lookup = 8'h2D; 8'hFB: s_box_lookup = 8'h0F;
        8'hFC: s_box_lookup = 8'hB0; 8'hFD: s_box_lookup = 8'h54; 8'hFE: s_box_lookup = 8'hBB; 8'hFF: s_box_lookup = 8'h16;


    default: s_box_lookup=8'h00;
    endcase
end
endfunction


//---------------------------PERMUTATING OF THE NIBBLES------------------------------

function[7:0] swapping_nibbles;
input [7:0] in;
reg [3:0] high,low;
begin 
    high=get_upper(in);
    low=get_lower(in);
    swapping_nibbles=mergingnibbles(low,high);
end
endfunction


//-----------------------------ENCRYPTING THE PIPELINE-------------------------------------


assign s_box_val=s_box_lookup(data_input);
assign perm_val=swapping_nibbles(s_box_val);
assign xor_val=perm_val ^ KEY;
assign data_output=xor_val;

endmodule

Assignment 1 2025EET2478/Verilogfiles(GROUP_C)/verifying.v
//-----------------------------------------VERIFICATION MODULE-------------------------------------------

//what is this module?
/*The verification module acts as a built-in checker that compares the computed hash against 
the expected hash and generates a binary verified flag */


module verify_spn(
    input wire [7:0] plaintext,       // Original input text
    input wire [7:0] expected_hash,   // Hash received/stored for verification
    output wire [7:0] ciphertext,     // Ciphertext 
    output wire [7:0] hash_val,       // Hash computed
    output wire verified              // 1 if hashes match, else 0
);

    //--------------------Internal wires--------------------
    wire [7:0] enc_out;
    wire [7:0] xor_val;
    wire [7:0] shifted_val;

    //--------------------Encryption------------------------
    encrypt_spn enc_inst (
        .data_input(plaintext),
        .data_output(enc_out),
        .s_box_val(),          
        .perm_val()           
    );

    //--------------------Hashing---------------------------
    hash_spn hash_inst (
        .data_in(enc_out),
        .hash_out(hash_val),
        .xor_val(xor_val),
        .shifted_val(shifted_val)
    );

    //--------------------Verification----------------------
    assign ciphertext = enc_out;
    assign verified = (hash_val == expected_hash);

endmodule

Assignment 1 2025EET2478/Verilogfiles(GROUP_C)/testbench.v
//---------------------------------------CREATING A TEST BENCH FOR 8-BIT SPN CIPHER--------------------------
//---------------------------------------ENCRYPT + DECRYPT + HASH + VERIFY-----------------------------------------

//what is test bench used for?
/* A test bench mainly works as a simulator for verifying the correctness and the functionality
 of the digital design. */

module tb_verify_spn;

    // Testbench signals
    reg  [7:0] plaintext;                    //8 bit input texxt
    reg  [7:0] expected_hash;                //expected hash value
    wire [7:0] ciphertext;                   //8 bit cipher text
    wire [7:0] hash_val;                     //hash value
    wire verified;

    // Instantiating the Design under test unit for testing
    verify_spn uut (
        .plaintext(plaintext),
        .expected_hash(expected_hash),
        .ciphertext(ciphertext),
        .hash_val(hash_val),
        .verified(verified)
    );

    // here we have created a function for running the test cases
    task run_test;
        input [7:0] pt;
        input [7:0] exp_hash;
        input  exp_result;
        reg [39:0] result_str;
        begin
            plaintext = pt;
            expected_hash = exp_hash;
            #10;  
            $display("| %8h | %10h | %8h | %13h | %8b |",
                     plaintext, ciphertext, hash_val, expected_hash, verified);
        end
    endtask

    // here we are generating the waveforms
    initial begin
    $dumpfile("wave.vcd");       // Name of the waveform file
    $dumpvars(0, tb_verify_spn); // Dump all signals in the testbench hierarchy
end


    // Test sequence
    integer i;
    reg [7:0] rand_in;

    initial begin
        // Table header format
        $display("---------------------------------------------------------------------------------------------");
        $display("| PLAINTEXT | CIPHERTEXT | HASH_VAL | EXPECTED_HASH | VERIFIED |");
        $display("---------------------------------------------------------------------------------------------");

        //The three fixed test cases
        run_test(8'h41, 8'hE0, 1);    //1st Test case
        run_test(8'hFF, 8'h84, 1);    //2nd Test case
        run_test(8'h27, 8'h30, 1);    //3rd Test case



        // Random test cases
        $display("---------------HERE WE ARE RUNNING SOME RANDOM TEST CASES ---------------");
        for (i=0;i<10;i=i+1) 
        begin
            rand_in = $random;   // random 8-bit value
            plaintext = rand_in;

            #10; 

            run_test(rand_in, hash_val, 1);
            run_test(rand_in, hash_val ^ 8'hFF, 0); 
        end

        $display("---------------------------------------------------------------------------------------------");
        $display("--------------- THANK YOU, ALL THE TEST CASES ARE COMPLETED........GOODBYE ---------------");
        $finish;
    end

endmodule

Assignment 1 2025EET2478/Verilogfiles(GROUP_C)/wave.vcd
$date
	Sun Sep 07 14:38:10 2025
$end
$version
	Icarus Verilog
$end
$timescale
	1s
$end
$scope module tb_verify_spn $end
$var wire 1 ! verified $end
$var wire 8 " hash_val [7:0] $end
$var wire 8 # ciphertext [7:0] $end
$var reg 8 $ expected_hash [7:0] $end
$var reg 8 % plaintext [7:0] $end
$var reg 8 & rand_in [7:0] $end
$var integer 32 ' i [31:0] $end
$scope module uut $end
$var wire 8 ( ciphertext [7:0] $end
$var wire 8 ) expected_hash [7:0] $end
$var wire 8 * plaintext [7:0] $end
$var wire 8 + xor_val [7:0] $end
$var wire 1 ! verified $end
$var wire 8 , shifted_val [7:0] $end
$var wire 8 - hash_val [7:0] $end
$var wire 8 . enc_out [7:0] $end
$scope module enc_inst $end
$var wire 8 / data_input [7:0] $end
$var wire 8 0 data_output [7:0] $end
$var wire 8 1 xor_val [7:0] $end
$var wire 8 2 s_box_val [7:0] $end
$var wire 8 3 perm_val [7:0] $end
$scope function get_lower $end
$var reg 8 4 in [7:0] $end
$upscope $end
$scope function get_upper $end
$var reg 8 5 in [7:0] $end
$upscope $end
$scope function mergingnibbles $end
$var reg 4 6 high [3:0] $end
$var reg 4 7 low [3:0] $end
$upscope $end
$scope function s_box_lookup $end
$var reg 8 8 in [7:0] $end
$upscope $end
$scope function swapping_nibbles $end
$var reg 4 9 high [3:0] $end
$var reg 8 : in [7:0] $end
$var reg 4 ; low [3:0] $end
$upscope $end
$upscope $end
$scope module hash_inst $end
$var wire 8 < data_in [7:0] $end
$var wire 8 = hash_out [7:0] $end
$var wire 8 > xor_val [7:0] $end
$var wire 8 ? shifted_val [7:0] $end
$scope function left_shiftingby_2 $end
$var reg 8 @ val [7:0] $end
$upscope $end
$scope function xoring_withthe_key $end
$var reg 8 A val [7:0] $end
$upscope $end
$upscope $end
$upscope $end
$scope task run_test $end
$var reg 8 B exp_hash [7:0] $end
$var reg 1 C exp_result $end
$var reg 8 D pt [7:0] $end
$upscope $end
$upscope $end
$enddefinitions $end
#0
$dumpvars
b1000001 D
1C
b11100000 B
b1100010 A
b111000 @
b11100000 ?
b111000 >
b11100000 =
b1100010 <
b11 ;
b10000011 :
b1000 9
b1000001 8
b1000 7
b11 6
b10000011 5
b10000011 4
b111000 3
b10000011 2
b1100010 1
b1100010 0
b1000001 /
b1100010 .
b11100000 -
b11100000 ,
b111000 +
b1000001 *
b11100000 )
b1100010 (
bx '
bx &
b1000001 %
b11100000 $
b1100010 #
b11100000 "
1!
$end
#10
b10000100 "
b10000100 -
b10000100 =
b10000100 ,
b10000100 ?
b1100001 @
b1100001 +
b1100001 >
b111011 A
b111011 #
b111011 (
b111011 .
b111011 0
b111011 <
b111011 1
b1100001 3
b110 6
b1 7
b110 ;
b10110 4
b1 9
b10110 5
b10110 :
b10110 2
b11111111 8
1!
b10000100 $
b10000100 )
b11111111 %
b11111111 *
b11111111 /
b10000100 B
b11111111 D
#20
b110000 "
b110000 -
b110000 =
b110000 ,
b110000 ?
b11001100 @
b11001100 +
b11001100 >
b10010110 A
b10010110 #
b10010110 (
b10010110 .
b10010110 0
b10010110 <
b10010110 1
b11001100 3
b1100 6
b1100 7
b1100 ;
b11001100 4
b1100 9
b11001100 5
b11001100 :
b11001100 2
b100111 8
1!
b110000 $
b110000 )
b100111 %
b100111 *
b100111 /
b110000 B
b100111 D
#30
0!
b10001100 "
b10001100 -
b10001100 =
b10001100 ,
b10001100 ?
b1100011 @
b1100011 +
b1100011 >
b111001 A
b111001 #
b111001 (
b111001 .
b111001 0
b111001 <
b111001 1
b1100011 3
b110 6
b11 7
b110 ;
b110110 4
b11 9
b110110 5
b110110 :
b110110 2
b100100 8
b100100 %
b100100 *
b100100 /
b100100 &
b0 '
#40
1!
b10001100 $
b10001100 )
b10001100 B
b100100 D
#50
0!
b1110011 $
b1110011 )
0C
b1110011 B
#60
b0 "
b0 -
b0 =
b0 ,
b0 ?
b11000000 @
b11000000 +
b11000000 >
b10011010 A
b10011010 #
b10011010 (
b10011010 .
b10011010 0
b10011010 <
b10011010 1
b11000000 3
b1100 6
b0 7
b1100 ;
b1100 4
b0 9
b1100 5
b1100 :
b1100 2
b10000001 8
b10000001 %
b10000001 *
b10000001 /
b10000001 &
b1 '
#70
1!
b0 $
b0 )
1C
b0 B
b10000001 D
#80
0!
b11111111 $
b11111111 )
0C
b11111111 B
#90
b1000000 "
b1000000 -
b1000000 =
b1000000 ,
b1000000 ?
b10000 @
b10000 +
b10000 >
b1001010 A
b1001010 #
b1001010 (
b1001010 .
b1001010 0
b1001010 <
b1001010 1
b10000 3
b1 6
b1 ;
b1 4
b1 5
b1 :
b1 2
b1001 8
b1001 %
b1001 *
b1001 /
b1001 &
b10 '
#100
1!
b1000000 $
b1000000 )
1C
b1000000 B
b1001 D
#110
0!
b10111111 $
b10111111 )
0C
b10111111 B
#120
b11111100 "
b11111100 -
b11111100 =
b11111100 ,
b11111100 ?
b10111111 @
b10111111 +
b10111111 >
b11100101 A
b11100101 #
b11100101 (
b11100101 .
b11100101 0
b11100101 <
b11100101 1
b10111111 3
b1011 6
b1111 7
b1011 ;
b11111011 4
b1111 9
b11111011 5
b11111011 :
b11111011 2
b1100011 8
b1100011 %
b1100011 *
b1100011 /
b1100011 &
b11 '
#130
1!
b11111100 $
b11111100 )
1C
b11111100 B
b1100011 D
#140
0!
b11 $
b11 )
0C
b11 B
#150
b11110100 "
b11110100 -
b11110100 =
b11110100 ,
b11110100 ?
b1111101 @
b1111101 +
b1111101 >
b100111 A
b100111 #
b100111 (
b100111 .
b100111 0
b100111 <
b100111 1
b1111101 3
b111 6
b1101 7
b111 ;
b11010111 4
b1101 9
b11010111 5
b11010111 :
b11010111 2
b1101 8
b1101 %
b1101 *
b1101 /
b1101 &
b100 '
#160
1!
b11110100 $
b11110100 )
1C
b11110100 B
b1101 D
#170
0!
b1011 $
b1011 )
0C
b1011 B
#180
b1010100 "
b1010100 -
b1010100 =
b1010100 ,
b1010100 ?
b11010101 @
b11010101 +
b11010101 >
b10001111 A
b10001111 #
b10001111 (
b10001111 .
b10001111 0
b10001111 <
b10001111 1
b11010101 3
b1101 6
b101 7
b1101 ;
b1011101 4
b101 9
b1011101 5
b1011101 :
b1011101 2
b10001101 8
b10001101 %
b10001101 *
b10001101 /
b10001101 &
b101 '
#190
1!
b1010100 $
b1010100 )
1C
b1010100 B
b10001101 D
#200
0!
b10101011 $
b10101011 )
0C
b10101011 B
#210
b1010000 "
b1010000 -
b1010000 =
b1010000 ,
b1010000 ?
b11010100 @
b11010100 +
b11010100 >
b10001110 A
b10001110 #
b10001110 (
b10001110 .
b10001110 0
b10001110 <
b10001110 1
b11010100 3
b100 7
b1001101 4
b100 9
b1001101 5
b1001101 :
b1001101 2
b1100101 8
b1100101 %
b1100101 *
b1100101 /
b1100101 &
b110 '
#220
1!
b1010000 $
b1010000 )
1C
b1010000 B
b1100101 D
#230
0!
b10101111 $
b10101111 )
0C
b10101111 B
#240
b1110000 "
b1110000 -
b1110000 =
b1110000 ,
b1110000 ?
b10011100 @
b10011100 +
b10011100 >
b11000110 A
b11000110 #
b11000110 (
b11000110 .
b11000110 0
b11000110 <
b11000110 1
b10011100 3
b1001 6
b1100 7
b1001 ;
b11001001 4
b1100 9
b11001001 5
b11001001 :
b11001001 2
b10010 8
b10010 %
b10010 *
b10010 /
b10010 &
b111 '
#250
1!
b1110000 $
b1110000 )
1C
b1110000 B
b10010 D
#260
0!
b10001111 $
b10001111 )
0C
b10001111 B
#270
b11100 "
b11100 -
b11100 =
b11100 ,
b11100 ?
b11000111 @
b11000111 +
b11000111 >
b10011101 A
b10011101 #
b10011101 (
b10011101 .
b10011101 0
b10011101 <
b10011101 1
b11000111 3
b1100 6
b111 7
b1100 ;
b1111100 4
b111 9
b1111100 5
b1111100 :
b1111100 2
b1 8
b1 %
b1 *
b1 /
b1 &
b1000 '
#280
1!
b11100 $
b11100 )
1C
b11100 B
b1 D
#290
0!
b11100011 $
b11100011 )
0C
b11100011 B
#300
b11110100 "
b11110100 -
b11110100 =
b11110100 ,
b11110100 ?
b1111101 @
b1111101 +
b1111101 >
b100111 A
b100111 #
b100111 (
b100111 .
b100111 0
b100111 <
b100111 1
b1111101 3
b111 6
b1101 7
b111 ;
b11010111 4
b1101 9
b11010111 5
b11010111 :
b11010111 2
b1101 8
b1101 %
b1101 *
b1101 /
b1101 &
b1001 '
#310
1!
b11110100 $
b11110100 )
1C
b11110100 B
b1101 D
#320
0!
b1011 $
b1011 )
0C
b1011 B
#330
b1010 '
